cloudbeds_pms_v1_3/__init__.py
cloudbeds_pms_v1_3/api_client.py
cloudbeds_pms_v1_3/api_response.py
cloudbeds_pms_v1_3/configuration.py
cloudbeds_pms_v1_3/exceptions.py
cloudbeds_pms_v1_3/py.typed
cloudbeds_pms_v1_3/rest.py
cloudbeds_pms_v1_3/api/__init__.py
cloudbeds_pms_v1_3/api/adjustment_api.py
cloudbeds_pms_v1_3/api/allotment_blocks_api.py
cloudbeds_pms_v1_3/api/app_settings_api.py
cloudbeds_pms_v1_3/api/authentication_api.py
cloudbeds_pms_v1_3/api/currency_api.py
cloudbeds_pms_v1_3/api/custom_fields_api.py
cloudbeds_pms_v1_3/api/dashboard_api.py
cloudbeds_pms_v1_3/api/emails_api.py
cloudbeds_pms_v1_3/api/groups_api.py
cloudbeds_pms_v1_3/api/guest_api.py
cloudbeds_pms_v1_3/api/hotel_api.py
cloudbeds_pms_v1_3/api/house_account_api.py
cloudbeds_pms_v1_3/api/housekeeping_api.py
cloudbeds_pms_v1_3/api/integration_api.py
cloudbeds_pms_v1_3/api/item_api.py
cloudbeds_pms_v1_3/api/package_api.py
cloudbeds_pms_v1_3/api/payment_api.py
cloudbeds_pms_v1_3/api/rate_api.py
cloudbeds_pms_v1_3/api/reservation_api.py
cloudbeds_pms_v1_3/api/room_api.py
cloudbeds_pms_v1_3/api/taxes_and_fees_api.py
cloudbeds_pms_v1_3/api/user_api.py
cloudbeds_pms_v1_3/models/__init__.py
cloudbeds_pms_v1_3/models/delete_adjustment_response.py
cloudbeds_pms_v1_3/models/delete_guest_note_response.py
cloudbeds_pms_v1_3/models/delete_reservation_note_response.py
cloudbeds_pms_v1_3/models/delete_room_block_response.py
cloudbeds_pms_v1_3/models/delete_webhook_response.py
cloudbeds_pms_v1_3/models/get_allotment_blocks_response.py
cloudbeds_pms_v1_3/models/get_allotment_blocks_response_data_inner.py
cloudbeds_pms_v1_3/models/get_allotment_blocks_response_data_inner_allotment_intervals_inner.py
cloudbeds_pms_v1_3/models/get_allotment_blocks_response_data_inner_allotment_intervals_inner_availability_inner.py
cloudbeds_pms_v1_3/models/get_allotment_blocks_response_data_inner_allotment_intervals_inner_restrictions.py
cloudbeds_pms_v1_3/models/get_allotment_blocks_response_data_inner_auto_release_inner.py
cloudbeds_pms_v1_3-1.8.0.dist-info/licenses/LICENSE
cloudbeds_pms_v1_3-1.8.0.dist-info/METADATA
cloudbeds_pms_v1_3-1.8.0.dist-info/WHEEL
cloudbeds_pms_v1_3-1.8.0.dist-info/top_level.txt
cloudbeds_pms_v1_3-1.8.0.dist-info/RECORD
